wealth_discovery_destiny-1.0.1.dist-info/METADATA
wealth_discovery_destiny-1.0.1.dist-info/WHEEL
wealth_discovery_destiny-1.0.1.dist-info/licenses/LICENSE
destiny/backtest_strategy.py
destiny/tests/download_history_data.py
destiny/tests/test_1.py
destiny/tests/backtest.py
destiny/__init__.py
destiny/strategy.py
destiny/destiny.pyi
destiny/backtest.py
destiny/destiny.cpython-311-darwin.so
wealth_discovery_destiny-1.0.1.dist-info/RECORD
