Metadata-Version: 2.4
Name: wealth-discovery-destiny
Version: 1.0.1
Classifier: Programming Language :: Rust
Classifier: Programming Language :: Python :: Implementation :: CPython
Classifier: Programming Language :: Python :: Implementation :: PyPy
Requires-Dist: pandas==2.2.3
Requires-Dist: numpy==1.26.4
Requires-Dist: setproctitle==1.3.4
License-File: LICENSE
Summary: 天命量化库
Author: <Husky> <husky.robot.dog@gmail.com>
Author-email: <Husky> <husky.robot.dog@gmail.com>
Requires-Python: >=3.8
Project-URL: Source Code, https://github.com/wealth-discovery/destiny
